gradools/__init__.py
gradools/canvastools.py
gradools/check.py
gradools/mconfig.py
gradools/mkfb.py
gradools/mkstable.py
gradools/report.py
gradools/stinit.py
gradools/tests/test_canvastools.py
gradools/tests/test_check.py
gradools/tests/test_mconfig.py
gradools/tests/test_report.py
gradools/tests/test_stinit.py
gradools/tests/data/full_gb_example.csv
gradools/tests/data/marks_2017.txt
gradools-0.1a2.dist-info/entry_points.txt
gradools-0.1a2.dist-info/LICENSE
gradools-0.1a2.dist-info/WHEEL
gradools-0.1a2.dist-info/METADATA
gradools-0.1a2.dist-info/RECORD
