Metadata-Version: 2.1
Name: gradools
Version: 0.1a2
Summary: gradools
Home-page: https://github.com/matthew-brett/gradools
Author: Matthew Brett
Author-email: matthew.brett@gmail.com
Requires-Python: >=3.6
Classifier: License :: OSI Approved :: BSD License
Classifier: Programming Language :: Python :: 3
Requires-Dist: pytoml
Requires-Dist: pandas
Requires-Dist: regex
